stac_vrt.py
stac_vrt-1.0.3.dist-info/LICENSE
stac_vrt-1.0.3.dist-info/WHEEL
stac_vrt-1.0.3.dist-info/METADATA
stac_vrt-1.0.3.dist-info/RECORD
